isolate_proto/__init__.py
isolate_proto/configuration.py
isolate_proto/controller.proto
isolate_proto/controller_pb2.py
isolate_proto/controller_pb2.pyi
isolate_proto/controller_pb2_grpc.py
isolate_proto/py.typed
isolate_proto/health/__init__.py
isolate_proto/health/health.proto
isolate_proto/health/health_pb2.py
isolate_proto/health/health_pb2.pyi
isolate_proto/health/health_pb2_grpc.py
isolate_proto-0.30.1.dist-info/METADATA
isolate_proto-0.30.1.dist-info/WHEEL
isolate_proto-0.30.1.dist-info/top_level.txt
isolate_proto-0.30.1.dist-info/RECORD
